CharmCord/__init__.py
CharmCord/all_functions.py
CharmCord/CharmErrorHandling.py
CharmCord/functions/__init__.py
CharmCord/functions/Channels/__init__.py
CharmCord/functions/Channels/channelCategoryID.py
CharmCord/functions/Channels/channelCategoryName.py
CharmCord/functions/Channels/channelChangedRoles.py
CharmCord/functions/Channels/channelCreated.py
CharmCord/functions/Channels/channelDelay.py
CharmCord/functions/Channels/channelID.py
CharmCord/functions/Channels/channelMention.py
CharmCord/functions/Channels/channelName.py
CharmCord/functions/Channels/channelNsfw.py
CharmCord/functions/Channels/channelPosition.py
CharmCord/functions/Channels/channelType.py
CharmCord/functions/Channels/channelURL.py
CharmCord/functions/Channels/threadAutoArchive.py
CharmCord/functions/Client/__init__.py
CharmCord/functions/Client/botAvatar.py
CharmCord/functions/Client/botGuilds.py
CharmCord/functions/Client/botID.py
CharmCord/functions/Client/botMention.py
CharmCord/functions/Client/botName.py
CharmCord/functions/Client/ping.py
CharmCord/functions/clientActivity.py
CharmCord/functions/Events/__init__.py
CharmCord/functions/Events/_options_.py
CharmCord/functions/Events/deletedChannel.py
CharmCord/functions/Events/memberJoined.py
CharmCord/functions/Events/newChannel.py
CharmCord/functions/Events/oldChannel.py
CharmCord/functions/Events/onMessage.py
CharmCord/functions/Events/reactionAdded.py
CharmCord/functions/Events/reactionRemoved.py
CharmCord/functions/Guilds/__init__.py
CharmCord/functions/Guilds/guildID.py
CharmCord/functions/Guilds/guildName.py
CharmCord/functions/Guilds/guildTextChannels.py
CharmCord/functions/Messages/__init__.py
CharmCord/functions/Messages/_btnOpts_.py
CharmCord/functions/Messages/addButton.py
CharmCord/functions/Messages/addDropdown.py
CharmCord/functions/Messages/buttonSend.py
CharmCord/functions/Messages/defer.py
CharmCord/functions/Messages/deleteMessage.py
CharmCord/functions/Messages/dropdownOption.py
CharmCord/functions/Messages/editMessage.py
charmcord-1.1.7.dist-info/LICENSE
charmcord-1.1.7.dist-info/METADATA
charmcord-1.1.7.dist-info/WHEEL
charmcord-1.1.7.dist-info/RECORD
