Metadata-Version: 2.3
Name: charmcord
Version: 1.1.7
Summary: CharmCord is the best python string-based package for Discord bot devs
License: MIT
Author: Jade
Requires-Python: >=3.8,<4.0
Classifier: License :: OSI Approved :: MIT License
Classifier: Operating System :: OS Independent
Classifier: Programming Language :: Python :: 3
Classifier: Programming Language :: Python :: 3.8
Classifier: Programming Language :: Python :: 3.9
Classifier: Programming Language :: Python :: 3.10
Classifier: Programming Language :: Python :: 3.11
Classifier: Programming Language :: Python :: 3.12
Classifier: Programming Language :: Python :: 3.13
Requires-Dist: colorama (>=0.4.6,<0.5.0)
Requires-Dist: discord-py (>=2.3.0,<3.0.0)
Requires-Dist: pytz (>=2023.3)
